[
  {
    "name": "BUSD Token",
    "symbol": "BUSD",
    "address": "0xe9e7CEA3DedcA5984780Bafc599bD69ADd087D56",
    "chainId": 56,
    "decimals": 18,
    "logoURI": "https://bscscan.com/token/images/busd_32.png"
  },
  {
    "name": "Tether USD",
    "symbol": "USDT",
    "address": "0x55d398326f99059fF775485246999027B3197955",
    "chainId": 56,
    "decimals": 18,
    "logoURI": "https://bscscan.com/token/images/busdt_32.png"
  },
  {
    "name": "Dai Token",
    "symbol": "DAI",
    "address": "0x1AF3F329e8BE154074D8769D1FFa4eE058B1DBc3",
    "chainId": 56,
    "decimals": 18,
    "logoURI": "https://bscscan.com/token/images/dai_32.png"
  },
  {
    "name": "Binance-Peg USD Coin",
    "symbol": "USDC",
    "address": "0x8AC76a51cc950d9822D68b83fE1Ad97B32Cd580d",
    "chainId": 56,
    "decimals": 18,
    "logoURI": "https://bscscan.com/token/images/centre-usdc_28.png"
  },
  {
    "name": "UST Token",
    "symbol": "UST",
    "address": "0x23396cF899Ca06c4472205fC903bDB4de249D6fC",
    "chainId": 56,
    "decimals": 18,
    "logoURI": "https://bscscan.com/token/images/terra-ust_32.png"
  },
  {
    "name": "BTCB Token",
    "symbol": "BTCB",
    "address": "0x7130d2A12B9BCbFAe4f2634d864A1Ee1Ce3Ead9c",
    "chainId": 56,
    "decimals": 18,
    "logoURI": "https://bscscan.com/token/images/btcb_32.png"
  },
  {
    "name": "WBNB Token",
    "symbol": "WBNB",
    "address": "0xbb4CdB9CBd36B01bD1cBaEBF2De08d9173bc095c",
    "chainId": 56,
    "decimals": 18,
    "logoURI": "https://bscscan.com/token/images/binance_32.png"
  },
  {
    "name": "Cardano Token",
    "symbol": "ADA",
    "address": "0x3EE2200Efb3400fAbB9AacF31297cBdD1d435D47",
    "chainId": 56,
    "decimals": 18,
    "logoURI": "https://bscscan.com/token/images/cardano_32.png"
  },
  {
    "name": "PancakeSwap Token",
    "symbol": "CAKE",
    "address": "0x0E09FaBB73Bd3Ade0a17ECC321fD13a19e81cE82",
    "chainId": 56,
    "decimals": 18,
    "logoURI": "https://bscscan.com/token/images/pancake_32.png"
  },
  {
    "name": "Polkadot Token",
    "symbol": "DOT",
    "address": "0x7083609fCE4d1d8Dc0C979AAb8c869Ea2C873402",
    "chainId": 56,
    "decimals": 18,
    "logoURI": "https://bscscan.com/token/images/polkadot_32.png"
  },
  {
    "name": "XRP Token",
    "symbol": "XRP",
    "address": "0x1D2F0da169ceB9fC7B3144628dB156f3F6c60dBE",
    "chainId": 56,
    "decimals": 18,
    "logoURI": "https://bscscan.com/token/images/xrp_32.png"
  }
]